LICENSE
pyrate_limiter_concord/__init__.py
pyrate_limiter_concord/bucket.py
pyrate_limiter_concord/constants.py
pyrate_limiter_concord/exceptions.py
pyrate_limiter_concord/limit_context_decorator.py
pyrate_limiter_concord/limiter.py
pyrate_limiter_concord/py.typed
pyrate_limiter_concord/request_rate.py
pyrate_limiter_concord/sqlite_bucket.py
pyrate_limiter_concord-2.9.3.dist-info/LICENSE
pyrate_limiter_concord-2.9.3.dist-info/WHEEL
pyrate_limiter_concord-2.9.3.dist-info/METADATA
pyrate_limiter_concord-2.9.3.dist-info/RECORD
